pvml/__init__.py
pvml/checks.py
pvml/classtree.py
pvml/cnn.py
pvml/dataset.py
pvml/gda.py
pvml/kmeans.py
pvml/ksvm.py
pvml/logistic_regression.py
pvml/mlp.py
pvml/multiclass_ksvm.py
pvml/multiclass_svm.py
pvml/multinomial_logistic.py
pvml/naivebayes.py
pvml/nearest_neighbor.py
pvml/normalization.py
pvml/pca.py
pvml/perceptron.py
pvml/rnn.py
pvml/svm.py
pvml/utils.py
pvml-0.4.0.dist-info/LICENSE
pvml-0.4.0.dist-info/METADATA
pvml-0.4.0.dist-info/WHEEL
pvml-0.4.0.dist-info/top_level.txt
pvml-0.4.0.dist-info/RECORD
