Metadata-Version: 2.1
Name: pvml
Version: 0.4.0
Summary: A small and simple machine learning library
Home-page: https://github.com/claudio-unipv/pvml
Author: Claudio Cusano
Author-email: claudio.cusano@unipv.it
License: UNKNOWN
Platform: UNKNOWN
Classifier: Programming Language :: Python :: 3
Classifier: License :: OSI Approved :: MIT License
Classifier: Operating System :: OS Independent
Requires-Python: >=3.6
Requires-Dist: Pillow (>=5.1.0)
Requires-Dist: matplotlib (>=2.1.0)
Requires-Dist: numpy (>=1.13.0)
